build/python/common/__init__.py
build/python/common/enums_pb2.py
build/python/common/shared_pb2.py
build/python/homepage/__init__.py
build/python/homepage/auth_pb2.py
build/python/homepage/endpoint_pb2.py
build/python/homepage/request_pb2.py
build/python/mypage/__init__.py
build/python/mypage/endpoint_pb2.py
build/python/mypage/request_pb2.py
build/python/mypage/response_pb2.py
build/python/payment/__init__.py
build/python/payment/endpoint_pb2.py
build/python/payment/model/amount_pb2.py
build/python/payment/model/payout_pb2.py
build/python/payment/model/transfer_pb2.py
build/python/payment/request_pb2.py
build/python/payment/response_pb2.py
build/python/pre_signed/__init__.py
build/python/pre_signed/pre_signed_pb2.py
idl_py_package-1.0.2.dist-info/METADATA
idl_py_package-1.0.2.dist-info/WHEEL
idl_py_package-1.0.2.dist-info/RECORD
