Metadata-Version: 2.1
Name: idl_py_package
Version: 1.0.2
Summary: IDL generated Python files
Author: Your Name
Author-email: your.email@example.com
Requires-Python: >=3.9,<4.0
Classifier: Programming Language :: Python :: 3
Classifier: Programming Language :: Python :: 3.9
Classifier: Programming Language :: Python :: 3.10
Classifier: Programming Language :: Python :: 3.11
Classifier: Programming Language :: Python :: 3.12
